phisfortmodule/__init__.py
phisfortmodule/h_repeatitivemethod.py
phisfortmodule-0.0.3.dist-info/METADATA
phisfortmodule-0.0.3.dist-info/WHEEL
phisfortmodule-0.0.3.dist-info/top_level.txt
phisfortmodule-0.0.3.dist-info/RECORD
